wikipedia_tablo_cekici/__init__.py
wikipedia_tablo_cekici/main.py
wikipedia_tablo_cekici/sayi_cevirici.py
wikipedia_tablo_cekici-1.0.4.dist-info/METADATA
wikipedia_tablo_cekici-1.0.4.dist-info/WHEEL
wikipedia_tablo_cekici-1.0.4.dist-info/top_level.txt
wikipedia_tablo_cekici-1.0.4.dist-info/RECORD
